{
  "default_rates": {
    "Bắp": 400000,
    "Nành": 400000,
    "Cám gạo": 270000,
    "Khác": 350000
  },
  "specific_rates": {
    "Bắp": 400000,
    "Nành": 400000,
    "Cám gạo": 270000,
    "Đá hạt": 350000,
    "Đá bột mịn": 350000,
    "DL-Methionine": 350000,
    "L-Lysine": 350000,
    "Bio-Choline": 350000,
    "Phytast": 350000,
    "Performix 0.25% layer": 350000,
    "Miamix": 350000,
    "Premix 0.25% layer": 350000,
    "Compound Enzyme FE808E": 350000,
    "Carophy Red": 350000,
    "P-Zym": 350000,
    "Immunewall": 350000,
    "Lysoforte Dry": 350000,
    "Defitox L1": 350000,
    "Men Ecobiol": 350000,
    "Lactic LD": 350000,
    "Sodium bicarbonate": 350000,
    "Bột đá mịn": 350000,
    "Muối": 350000
  },
  "updated_by": "User",
  "last_updated": "2025-07-28 11:31:43"
}